cqu_kx/__init__.py
cqu_kx/__main__.py
cqu_kx/core.py
cqu_kx/utils.py
cqu_kx/version.py
cqu_kx/config/__init__.py
cqu_kx/config/config.py
cqu_kx/config/config_default.yaml
cqu_kx-0.2.0.dist-info/LICENSE
cqu_kx-0.2.0.dist-info/METADATA
cqu_kx-0.2.0.dist-info/WHEEL
cqu_kx-0.2.0.dist-info/entry_points.txt
cqu_kx-0.2.0.dist-info/top_level.txt
cqu_kx-0.2.0.dist-info/RECORD
