Metadata-Version: 2.1
Name: cqu-kx
Version: 0.2.0
Summary: 第三方重庆大学课程可选人数查询工具－“快选!!”
Home-page: https://github.com/CQU-AI/cqu-kx
Author: CQU-AI
Author-email: peter@mail.loopy.tech
License: GPL License
Platform: all
Requires-Python: >=3.6
Requires-Dist: PyYAML (~=5.3.1)
Requires-Dist: requests (~=2.24.0)
Requires-Dist: cqu-jxgl (>=0.2.0)
Requires-Dist: beautifulsoup4 (~=4.9.1)
